irust_kernel/__init__.py
irust_kernel/__main__.py
irust_kernel/install.py
irust_kernel/kernel.py
irust_kernel-0.3.0.dist-info/WHEEL
irust_kernel-0.3.0.dist-info/METADATA
irust_kernel-0.3.0.dist-info/RECORD
