Metadata-Version: 2.1
Name: irust_kernel
Version: 0.3.0
Summary: A bash kernel for Jupyter
Author-email: Bedis Nbiba <bedisnbiba@gmail.com>
Classifier: Framework :: Jupyter
Classifier: License :: OSI Approved :: MIT License
Classifier: Programming Language :: Python :: 3
Requires-Dist: ipykernel
Project-URL: Source, https://github.com/sigmasd/irust/
